gpath/__init__.py
gpath/_compat.py
gpath/_gpath.py
gpath/platform.py
gpath/render.py
gpath/_rules/__init__.py
gpath/_rules/_common.py
gpath/_rules/_rules.py
generic_path-0.5.1.post1.dist-info/LICENSE.txt
generic_path-0.5.1.post1.dist-info/METADATA
generic_path-0.5.1.post1.dist-info/WHEEL
generic_path-0.5.1.post1.dist-info/top_level.txt
generic_path-0.5.1.post1.dist-info/RECORD
